{"Env":{"PF":[],"GF":[],"Plt":[{"Id":0,"Tt":1,"Of":0,"An":1,"FsT":[0,0.95,0],"Sz":[11,4],"Fs":[8.5,0,7]},{"Id":0,"Tt":1,"Of":0,"An":5,"FsT":[0,0.95,0],"Sz":[9,4],"Fs":[7.5,0,0]},{"Id":0,"Tt":1,"Of":0,"An":4,"FsT":[0,0.95,0],"Sz":[11,4],"Fs":[6.5,0,-7]},{"Id":0,"Tt":1,"Of":0,"An":4,"FsT":[0,0.95,0],"Sz":[4,11],"Fs":[3,0,3.5]},{"Id":0,"Tt":1,"Of":0,"An":1,"FsT":[0,0.95,0],"Sz":[4,11],"Fs":[12,0,-3.5]},{"Id":1,"Tt":1,"Of":0,"An":4,"FsT":[0,0.95,0],"Sz":[11,4],"Fs":[-8.5,0,7]},{"Id":1,"Tt":1,"Of":0,"An":5,"FsT":[0,0.95,0],"Sz":[9,4],"Fs":[-7.5,0,0]},{"Id":1,"Tt":1,"Of":0,"An":1,"FsT":[0,0.95,0],"Sz":[11,4],"Fs":[-6.5,0,-7]},{"Id":1,"Tt":1,"Of":0,"An":1,"FsT":[0,0.95,0],"Sz":[4,11],"Fs":[-3,0,3.5]},{"Id":1,"Tt":1,"Of":0,"An":4,"FsT":[0,0.95,0],"Sz":[4,11],"Fs":[-12,0,-3.5]}],"Clm":[],"SSD":[{"Sz":[2,2,2],"Pts":[[12,0.96,7],[3,0.96,7],[3,0.96,0],[12,0.96,0],[12,0.96,-7],[3,0.96,-7],[12,0.96,-7],[12,0.96,0],[3,0.96,0],[3,0.96,7]],"Sd":3,"Ps":1.5,"IRt":0,"IRn":0},{"Sz":[2,2,2],"Pts":[[-12,0.96,7],[-3,0.96,7],[-3,0.96,0],[-12,0.96,0],[-12,0.96,-7],[-3,0.96,-7],[-12,0.96,-7],[-12,0.96,0],[-3,0.96,0],[-3,0.96,7]],"Sd":3,"Ps":1.5,"IRt":0,"IRn":0}]},"Art":[{"Id":0,"Ps":[12.5,0.95,7.5]},{"Id":1,"Ps":[-12.5,0.95,7.5]},{"Id":2,"Ps":[-2.5,0.95,7.5]},{"Id":3,"Ps":[2.5,0.95,7.5]},{"Id":4,"Ps":[-2.5,0.95,-0.5]},{"Id":5,"Ps":[2.5,0.95,-0.5]},{"Id":6,"Ps":[-2.5,0.95,-7.5]},{"Id":7,"Ps":[2.5,0.95,-7.5]},{"Id":8,"Ps":[12.5,0.95,0.5]},{"Id":9,"Ps":[-12.5,0.95,0.5]},{"Id":10,"Ps":[12.5,0.95,-7.5]},{"Id":11,"Ps":[-12.5,0.95,-7.5]}],"Enm":[{"Tp":1,"Ps":[9.5,0,-3.5]},{"Tp":1,"Ps":[-9.5,0,-3.5]},{"Tp":2,"Ps":[0,0,-3.5]}],"Prb":[0,1.2,9],"LD":1.5}